acs_examine_student_assignment.py
acs_examine_student_assignment-1.0.0.dist-info/AUTHORS
acs_examine_student_assignment-1.0.0.dist-info/LICENSE
acs_examine_student_assignment-1.0.0.dist-info/METADATA
acs_examine_student_assignment-1.0.0.dist-info/WHEEL
acs_examine_student_assignment-1.0.0.dist-info/entry_points.txt
acs_examine_student_assignment-1.0.0.dist-info/top_level.txt
acs_examine_student_assignment-1.0.0.dist-info/RECORD
