Metadata-Version: 2.1
Name: acs-examine-student-assignment
Version: 1.0.0
Summary: Console app and Python API for automated assignment examination of our ACS students
Home-page: https://github.com/petarmaric/acs_examine_student_assignment
Author: Petar Maric
Author-email: petarmaric@uns.ac.rs
License: BSD
Platform: UNKNOWN
Classifier: Development Status :: 5 - Production/Stable
Classifier: Environment :: Console
Classifier: Intended Audience :: Developers
Classifier: Intended Audience :: Education
Classifier: License :: OSI Approved :: BSD License
Classifier: Operating System :: OS Independent
Classifier: Programming Language :: Python :: 2.7
Classifier: Topic :: Education
Classifier: Topic :: Utilities
Requires-Dist: smoke-test (~=1.0)
Provides-Extra: dev
Requires-Dist: pylint (~=1.9) ; extra == 'dev'
